django_dmf/__init__.py
django_dmf/asgi.py
django_dmf/settings.py
django_dmf/urls.py
django_dmf/wsgi.py
django_dmf-0.0.8.dist-info/licenses/LICENSE
dm/__init__.py
dm/admin.py
dm/apps.py
dm/constants.py
dm/models.py
dm/tests.py
dm/__pycache__/__init__.cpython-313.pyc
dm/__pycache__/admin.cpython-313.pyc
dm/__pycache__/apps.cpython-313.pyc
dm/__pycache__/constants.cpython-313.pyc
dm/__pycache__/models.cpython-313.pyc
dm/management/__init__.py
dm/management/__pycache__/__init__.cpython-313.pyc
dm/management/commands/__init__.py
dm/management/commands/migrate_data.py
dm/management/commands/__pycache__/__init__.cpython-313.pyc
dm/management/commands/__pycache__/migrate_data.cpython-313.pyc
dm/managers/__init__.py
dm/managers/__pycache__/__init__.cpython-313.pyc
dm/managers/dm/__init__.py
dm/managers/dm/core.py
dm/managers/dm/runner.py
dm/managers/dm/__pycache__/__init__.cpython-313.pyc
dm/managers/dm/__pycache__/core.cpython-313.pyc
dm/managers/dm/__pycache__/runner.cpython-313.pyc
dm/migrations/0001_initial.py
dm/migrations/__init__.py
dm/migrations/__pycache__/0001_initial.cpython-313.pyc
dm/migrations/__pycache__/__init__.cpython-313.pyc
dm/tasks/__init__.py
dm/tasks/__pycache__/__init__.cpython-313.pyc
dm/tasks/dm/__init__.py
dm/tasks/dm/base.py
dm/tasks/dm/__pycache__/__init__.cpython-313.pyc
dm/tasks/dm/__pycache__/base.cpython-313.pyc
dm/utils/__init__.py
dm/utils/logging.py
dm/utils/__pycache__/__init__.cpython-313.pyc
dm/utils/__pycache__/logging.cpython-313.pyc
dmf_test_app/__init__.py
dmf_test_app/admin.py
dmf_test_app/apps.py
dmf_test_app/constants.py
dmf_test_app/models.py
dmf_test_app/tests.py
dmf_test_app/views.py
dmf_test_app/dm/__init__.py
dmf_test_app/dm/tasks/__init__.py
dmf_test_app/dm/tasks/switch.py
dmf_test_app/managers/__init__.py
dmf_test_app/managers/switch.py
dmf_test_app/migrations/0001_initial.py
dmf_test_app/migrations/__init__.py
django_dmf-0.0.8.dist-info/METADATA
django_dmf-0.0.8.dist-info/WHEEL
django_dmf-0.0.8.dist-info/top_level.txt
django_dmf-0.0.8.dist-info/RECORD
